<?xml version="1.0" encoding="utf-8"?>
<TextureAtlas imagePath="itb_crowd_back.png">
	<!-- Created using the Spritesheet and XML generator -->
	<!-- https://uncertainprod.github.io/FNF-Spritesheet-XML-generator-Web -->
	<SubTexture name="itb_crowd_back instance 10000" x="1092" y="0" width="1091" height="520" frameX="-8" frameY="2" frameWidth="1106" frameHeight="516"/>
	<SubTexture name="itb_crowd_back instance 10001" x="0" y="1040" width="1092" height="513" frameX="-7" frameY="-5" frameWidth="1106" frameHeight="516"/>
	<SubTexture name="itb_crowd_back instance 10002" x="1092" y="1040" width="1091" height="509" frameX="-9" frameY="-9" frameWidth="1106" frameHeight="516"/>
	<SubTexture name="itb_crowd_back instance 10003" x="0" y="1553" width="1092" height="504" frameX="-3" frameY="-14" frameWidth="1106" frameHeight="516"/>
	<SubTexture name="itb_crowd_back instance 10004" x="2183" y="0" width="1094" height="503" frameX="-4" frameY="-15" frameWidth="1106" frameHeight="516"/>
	<SubTexture name="itb_crowd_back instance 10005" x="2183" y="503" width="1093" height="503" frameX="-7" frameY="-15" frameWidth="1106" frameHeight="516"/>
	<SubTexture name="itb_crowd_back instance 10006" x="0" y="520" width="1091" height="520" frameX="-5" frameY="2" frameWidth="1106" frameHeight="516"/>
	<SubTexture name="itb_crowd_back instance 10007" x="0" y="0" width="1092" height="520" frameX="-9" frameY="2" frameWidth="1106" frameHeight="516"/>
	<SubTexture name="itb_crowd_back instance 10008" x="1092" y="520" width="1091" height="520" frameX="-13" frameY="2" frameWidth="1106" frameHeight="516"/>
	<SubTexture name="itb_crowd_back instance 10009" x="1092" y="0" width="1091" height="520" frameX="-8" frameY="2" frameWidth="1106" frameHeight="516"/>
	<SubTexture name="itb_crowd_back instance 10010" x="1092" y="0" width="1091" height="520" frameX="-8" frameY="2" frameWidth="1106" frameHeight="516"/>
	<SubTexture name="itb_crowd_back instance 10011" x="1092" y="0" width="1091" height="520" frameX="-8" frameY="2" frameWidth="1106" frameHeight="516"/>
	<SubTexture name="itb_crowd_back instance 10012" x="1092" y="0" width="1091" height="520" frameX="-8" frameY="2" frameWidth="1106" frameHeight="516"/>
	<SubTexture name="itb_crowd_back instance 10013" x="1092" y="0" width="1091" height="520" frameX="-8" frameY="2" frameWidth="1106" frameHeight="516"/>
	<SubTexture name="itb_crowd_back instance 10014" x="1092" y="0" width="1091" height="520" frameX="-8" frameY="2" frameWidth="1106" frameHeight="516"/>
</TextureAtlas>